IDA/__init__.py
IDA/fragment.py
IDA/main.py
IDA/tools.py
IDA/tests/__init__.py
IDA/tests/test_main.py
IDA_pkg-0.0.2.dist-info/LICENSE
IDA_pkg-0.0.2.dist-info/METADATA
IDA_pkg-0.0.2.dist-info/WHEEL
IDA_pkg-0.0.2.dist-info/top_level.txt
IDA_pkg-0.0.2.dist-info/RECORD
