Metadata-Version: 2.1
Name: IDA-pkg
Version: 0.0.2
Summary: Python package for efficient dispersal of information that breaks a file of length N into n pieces, each of length N/m, so that every m pieces are sufficient to reconstruct the original file.
Home-page: https://github.com/mmtan/IDA
Author: mmtan
Author-email: mmtan830@gmail.com
License: UNKNOWN
Platform: UNKNOWN
Classifier: Programming Language :: Python :: 3
Classifier: License :: OSI Approved :: MIT License
Classifier: Operating System :: OS Independent
Requires-Python: >=3.6
